slurmrestpy/__init__.py
slurmrestpy/api_client.py
slurmrestpy/api_response.py
slurmrestpy/configuration.py
slurmrestpy/exceptions.py
slurmrestpy/py.typed
slurmrestpy/rest.py
slurmrestpy/api/__init__.py
slurmrestpy/api/slurm_api.py
slurmrestpy/api/slurmdb_api.py
slurmrestpy/models/__init__.py
slurmrestpy/models/v0040_account.py
slurmrestpy/models/v0040_account_short.py
slurmrestpy/models/v0040_accounting.py
slurmrestpy/models/v0040_accounting_allocated.py
slurmrestpy/models/v0040_accounts_add_cond.py
slurmrestpy/models/v0040_acct_gather_energy.py
slurmrestpy/models/v0040_assoc.py
slurmrestpy/models/v0040_assoc_max.py
slurmrestpy/models/v0040_assoc_max_jobs.py
slurmrestpy/models/v0040_assoc_max_jobs_per.py
slurmrestpy/models/v0040_assoc_max_per.py
slurmrestpy/models/v0040_assoc_max_per_account.py
slurmrestpy/models/v0040_assoc_max_tres.py
slurmrestpy/models/v0040_assoc_max_tres_group.py
slurmrestpy/models/v0040_assoc_max_tres_minutes.py
slurmrestpy/models/v0040_assoc_max_tres_per.py
slurmrestpy/models/v0040_assoc_min.py
slurmrestpy/models/v0040_assoc_rec_set.py
slurmrestpy/models/v0040_assoc_shares_obj_wrap.py
slurmrestpy/models/v0040_assoc_shares_obj_wrap_fairshare.py
slurmrestpy/models/v0040_assoc_shares_obj_wrap_tres.py
slurmrestpy/models/v0040_assoc_short.py
slurmrestpy/models/v0040_bf_exit_fields.py
slurmrestpy/models/v0040_cluster_rec.py
slurmrestpy/models/v0040_cluster_rec_associations.py
slurmrestpy/models/v0040_controller_ping.py
slurmrestpy/models/v0040_coord.py
slurmrestpy/models/v0040_cron_entry.py
slurmrestpy/models/v0040_float64_no_val.py
slurmrestpy/models/v0040_instance.py
slurmrestpy/models/v0040_job.py
slurmrestpy/models/v0040_job_array.py
slurmrestpy/models/v0040_job_array_response_msg_entry.py
slurmrestpy/models/v0040_job_desc_msg.py
slurmrestpy/models/v0040_job_desc_msg_rlimits.py
slurmrestpy/models/v0040_job_het.py
slurmrestpy/models/v0040_job_info.py
slurmrestpy/models/v0040_job_info_power.py
slurmrestpy/models/v0040_job_required.py
slurmrestpy-0.0.1.dist-info/METADATA
slurmrestpy-0.0.1.dist-info/WHEEL
slurmrestpy-0.0.1.dist-info/top_level.txt
slurmrestpy-0.0.1.dist-info/RECORD
