Metadata-Version: 2.4
Name: slurmrestpy
Version: 0.0.1
Summary: A Python package generated using openapi-generator for interacting with the Slurm REST API.
Author-email: Andy Stevens <andrew.stevens@gtri.gatech.edu>
Maintainer-email: Andrew Stevens <andrew.stevens@gtri.gatech.edu>
Project-URL: Homepage, https://github.com/AndyStevens98/slurmrestpy
Project-URL: Bug Reports, https://github.com/AndyStevens98/slurmrestpy/issues
Project-URL: Source, https://github.com/AndyStevens98/slurmrestpy
Keywords: slurmrestd,slurmrestapi
Requires-Python: >=3.8
Requires-Dist: urllib3<3.0.0,>=1.25.3
Requires-Dist: python-dateutil>=2.8.2
Requires-Dist: pydantic>=2
Requires-Dist: typing-extensions>=4.7.1
Provides-Extra: dev
Requires-Dist: pytest>=7.2.1; extra == "dev"
Requires-Dist: pytest-cov>=2.8.1; extra == "dev"
Requires-Dist: tox>=3.9.0; extra == "dev"
Requires-Dist: ruff>=0.11.2; extra == "dev"
Requires-Dist: types-python-dateutil>=2.8.19.14; extra == "dev"
Requires-Dist: mypy>=1.5; extra == "dev"
